MANIFEST.in
README.md
VERSION
setup.cfg
setup.py
bin/feature-store-pyspark-dependency-jars
deps/jars/sagemaker-feature-store-spark-sdk.jar
sagemaker_feature_store_pyspark_3.2.egg-info/PKG-INFO
sagemaker_feature_store_pyspark_3.2.egg-info/SOURCES.txt
sagemaker_feature_store_pyspark_3.2.egg-info/dependency_links.txt
sagemaker_feature_store_pyspark_3.2.egg-info/not-zip-safe
sagemaker_feature_store_pyspark_3.2.egg-info/top_level.txt
src/feature_store_pyspark/FeatureStoreManager.py
src/feature_store_pyspark/__init__.py
src/feature_store_pyspark/wrapper.py
tests/test_feature_store_manager.py