Metadata-Version: 2.1
Name: sagemaker_feature_store_pyspark_3.2
Version: 1.1.3
Summary: Amazon SageMaker FeatureStore PySpark Bindings
Author: Amazon Web Services
License: Apache License 2.0
Keywords: ML Amazon AWS AI FeatureStore SageMaker
